Metadata-Version: 1.0
Name: simpletime
Version: 0.0.8
Summary: simple to date and time conver
Home-page: https://github.com/area0li/simpletime
Author: Area0 Li <area0cn@gmail.com>
Author-email: area0cn@gmail.com
License: Mozilla Public License 2.0
Platform: UNKNOWN
